Workbook

Sheet Relative cell reference
B3: Name | C3: Designation | D3: Basic Salary | E3: Bonus | F3: Net Pay
B4: Andy Jones | C4: Accountant | D4: 70000 | E4: 0.05 | F4: =D4+(D4*E4) -> 73500
B5: Nathan Benson | C5: Director | D5: 120000 | E5: 0.1 | F5: =D5+(D5*E5) -> 132000
B6: James Williams | C6: Manager | D6: 100000 | E6: 0.09 | F6: =D6+(D6*E6) -> 109000
B7: John Ray | C7: Staff | D7: 65000 | E7: 0.04 | F7: =D7+(D7*E7) -> 67600
B8: Lucy Tomson | C8: IT | D8: 20000 | E8: 0.02 | F8: =D8+(D8*E8) -> 20400
B9: Martins Clinton | C9: Admin | D9: 55000 | E9: 0.03 | F9: =D9+(D9*E9) -> 56650

Sheet Absolute cell ref
D2: Discount | E2: 0.07
B3: Product | C3: Customers | D3: Quantity | E3: Unit Price | F3: Total
B4: Shoe | C4: Kate | D4: 1 | E4: 9000 | F4: =D4*E4-(D4*E4*$E$2) -> 8370
B5: Bag | C5: Ben | D5: 2 | E5: 4500 | F5: =D5*E5-(D5*E5*$E$2) -> 8370
B6: Watch | C6: Daniel | D6: 1 | E6: 1500 | F6: =D6*E6-(D6*E6*$E$2) -> 1395
B7: Cap | C7: James | D7: 1 | E7: 150 | F7: =D7*E7-(D7*E7*$E$2) -> 139.5
B8: Laptop | C8: Lucy | D8: 1 | E8: 7000 | F8: =D8*E8-(D8*E8*$E$2) -> 6510
B9: Phone | C9: Nathan | D9: 2 | E9: 3500 | F9: =D9*E9-(D9*E9*$E$2) -> 6510

Sheet Mixed cell ref
I4: 0.05 | J4: 0.07
D5: Product | E5: Customers | F5: Gender | G5: Quantity | H5: Unit Price | I5: Discount1 | J5: Discount 2 | K5: Total
D6: Shoe | E6: Kate | F6: Female | G6: 1 | H6: 9000 | I6: =($G6*$H6)-($G6*$H6*I$4) -> 8550 | J6: =($G6*$H6)-($G6*$H6*J$4) -> 8370 | K6: =I6 -> 8550
D7: Bag | E7: Ben | F7: Male | G7: 2 | H7: 4500 | I7: =($G7*$H7)-($G7*$H7*I$4) -> 8550 | J7: =($G7*$H7)-($G7*$H7*J$4) -> 8370 | K7: =J7 -> 8370
D8: Watch | E8: Daniel | F8: Male | G8: 1 | H8: 1500 | I8: =($G8*$H8)-($G8*$H8*I$4) -> 1425 | J8: =($G8*$H8)-($G8*$H8*J$4) -> 1395 | K8: =J8 -> 1395
D9: Cap | E9: James | F9: Male | G9: 1 | H9: 150 | I9: =($G9*$H9)-($G9*$H9*I$4) -> 142.5 | J9: =($G9*$H9)-($G9*$H9*J$4) -> 139.5 | K9: =J9 -> 139.5
D10: Laptop | E10: Lucy | F10: Female | G10: 1 | H10: 7000 | I10: =($G10*$H10)-($G10*$H10*I$4) -> 6650 | J10: =($G10*$H10)-($G10*$H10*J$4) -> 6510 | K10: =I10 -> 6650
D11: Phone | E11: Nathan | F11: Male | G11: 2 | H11: 3500 | I11: =($G11*$H11)-($G11*$H11*I$4) -> 6650 | J11: =($G11*$H11)-($G11*$H11*J$4) -> 6510 | K11: =J11 -> 6510

Sheet 3d cell ref
C3: ABC Supermarket Sales for 2025
C4: Product | D4: January | E4: February | F4: March | G4: April | H4: May | I4: June | J4: July | K4: August | L4: September | M4: October | N4: November | O4: December | P4: Total
C5: Rice | D5: =SUM('North Branch:West Branch'!B3) -> 29689 | E5: =SUM('North Branch:West Branch'!C3) -> 24343 | F5: =SUM('North Branch:West Branch'!D3) -> 32866 | G5: =SUM('North Branch:West Branch'!E3) -> 28304 | H5: =SUM('North Branch:West Branch'!F3) -> 27850 | I5: =SUM('North Branch:West Branch'!G3) -> 33027 | J5: =SUM('North Branch:West Branch'!H3) -> 30510 | K5: =SUM('North Branch:West Branch'!I3) -> 26523 | ... O5: =SUM('North Branch:West Branch'!M3) -> 29242 | P5: =SUM(D5:O5) -> 352766
C6: Beans | D6: =SUM('North Branch:West Branch'!B4) -> 28180 | E6: =SUM('North Branch:West Branch'!C4) -> 27803 | F6: =SUM('North Branch:West Branch'!D4) -> 31661 | G6: =SUM('North Branch:West Branch'!E4) -> 29758 | H6: =SUM('North Branch:West Branch'!F4) -> 29692 | I6: =SUM('North Branch:West Branch'!G4) -> 30521 | J6: =SUM('North Branch:West Branch'!H4) -> 34255 | K6: =SUM('North Branch:West Branch'!I4) -> 35306 | ... O6: =SUM('North Branch:West Branch'!M4) -> 31468 | P6: =SUM(D6:O6) -> 369611
C7: Butter | D7: =SUM('North Branch:West Branch'!B5) -> 29199 | E7: =SUM('North Branch:West Branch'!C5) -> 33668 | F7: =SUM('North Branch:West Branch'!D5) -> 25875 | G7: =SUM('North Branch:West Branch'!E5) -> 33873 | H7: =SUM('North Branch:West Branch'!F5) -> 24384 | I7: =SUM('North Branch:West Branch'!G5) -> 29164 | J7: =SUM('North Branch:West Branch'!H5) -> 25544 | K7: =SUM('North Branch:West Branch'!I5) -> 28739 | ... O7: =SUM('North Branch:West Branch'!M5) -> 36545 | P7: =SUM(D7:O7) -> 356508
C8: Gum | D8: =SUM('North Branch:West Branch'!B6) -> 27012 | E8: =SUM('North Branch:West Branch'!C6) -> 31305 | F8: =SUM('North Branch:West Branch'!D6) -> 28364 | G8: =SUM('North Branch:West Branch'!E6) -> 31042 | H8: =SUM('North Branch:West Branch'!F6) -> 27310 | I8: =SUM('North Branch:West Branch'!G6) -> 33714 | J8: =SUM('North Branch:West Branch'!H6) -> 30451 | K8: =SUM('North Branch:West Branch'!I6) -> 28683 | ... O8: =SUM('North Branch:West Branch'!M6) -> 31767 | P8: =SUM(D8:O8) -> 367674
C9: Bread | D9: =SUM('North Branch:West Branch'!B7) -> 31110 | E9: =SUM('North Branch:West Branch'!C7) -> 28806 | F9: =SUM('North Branch:West Branch'!D7) -> 36215 | G9: =SUM('North Branch:West Branch'!E7) -> 25595 | H9: =SUM('North Branch:West Branch'!F7) -> 34957 | I9: =SUM('North Branch:West Branch'!G7) -> 34476 | J9: =SUM('North Branch:West Branch'!H7) -> 32913 | K9: =SUM('North Branch:West Branch'!I7) -> 31244 | ... O9: =SUM('North Branch:West Branch'!M7) -> 29431 | P9: =SUM(D9:O9) -> 382643
C10: Ice Cream | D10: =SUM('North Branch:West Branch'!B8) -> 30395 | E10: =SUM('North Branch:West Branch'!C8) -> 28533 | F10: =SUM('North Branch:West Branch'!D8) -> 27156 | G10: =SUM('North Branch:West Branch'!E8) -> 29932 | H10: =SUM('North Branch:West Branch'!F8) -> 33849 | I10: =SUM('North Branch:West Branch'!G8) -> 27892 | J10: =SUM('North Branch:West Branch'!H8) -> 29695 | K10: =SUM('North Branch:West Branch'!I8) -> 33035 | ... O10: =SUM('North Branch:West Branch'!M8) -> 34690 | P10: =SUM(D10:O10) -> 374121
C11: Milk | D11: =SUM('North Branch:West Branch'!B9) -> 27912 | E11: =SUM('North Branch:West Branch'!C9) -> 29271 | F11: =SUM('North Branch:West Branch'!D9) -> 26906 | G11: =SUM('North Branch:West Branch'!E9) -> 27131 | H11: =SUM('North Branch:West Branch'!F9) -> 28237 | I11: =SUM('North Branch:West Branch'!G9) -> 24075 | J11: =SUM('North Branch:West Branch'!H9) -> 35015 | K11: =SUM('North Branch:West Branch'!I9) -> 32587 | ... O11: =SUM('North Branch:West Branch'!M9) -> 28799 | P11: =SUM(D11:O11) -> 350870
C12: Milo | D12: =SUM('North Branch:West Branch'!B10) -> 30360 | E12: =SUM('North Branch:West Branch'!C10) -> 32101 | F12: =SUM('North Branch:West Branch'!D10) -> 33909 | G12: =SUM('North Branch:West Branch'!E10) -> 31917 | H12: =SUM('North Branch:West Branch'!F10) -> 33217 | I12: =SUM('North Branch:West Branch'!G10) -> 35909 | J12: =SUM('North Branch:West Branch'!H10) -> 27885 | K12: =SUM('North Branch:West Branch'!I10) -> 31695 | ... O12: =SUM('North Branch:West Branch'!M10) -> 27915 | P12: =SUM(D12:O12) -> 371462
C14: Grand total | P14: =SUM(P5:P12) -> 2925655

Sheet North Branch
A1: ABC Supermarket Sales for 2025
A2: Product | B2: January | C2: February | D2: March | E2: April | F2: May | G2: June | H2: July | I2: August | J2: September | K2: October | L2: November | M2: December | N2: Total
A3: Rice | B3: 6730 | C3: 5224 | D3: 9768 | E3: 5703 | F3: 6561 | G3: 9326 | H3: 6568 | I3: 7952 | J3: 7066 | K3: 8928 | L3: 5470 | M3: 5452 | N3: =SUM(B3:M3) -> 84748
A4: Beans | B4: 6106 | C4: 8173 | D4: 7608 | E4: 9510 | F4: 9514 | G4: 7513 | H4: 8296 | I4: 8454 | J4: 8193 | K4: 7320 | L4: 5183 | M4: 7858 | N4: =SUM(B4:M4) -> 93728
A5: Butter | B5: 7434 | C5: 9136 | D5: 5329 | E5: 8106 | F5: 6464 | G5: 8504 | H5: 6011 | I5: 8226 | J5: 5947 | K5: 5074 | L5: 9897 | M5: 9263 | N5: =SUM(B5:M5) -> 89391
A6: Gum | B6: 6203 | C6: 8323 | D6: 6815 | E6: 8635 | F6: 8517 | G6: 8533 | H6: 8821 | I6: 5377 | J6: 7805 | K6: 7052 | L6: 5148 | M6: 7736 | N6: =SUM(B6:M6) -> 88965
A7: Bread | B7: 8163 | C7: 6096 | D7: 9694 | E7: 5161 | F7: 9118 | G7: 8946 | H7: 8459 | I7: 9023 | J7: 5542 | K7: 8640 | L7: 9789 | M7: 7448 | N7: =SUM(B7:M7) -> 96079
A8: Ice Cream | B8: 5793 | C8: 5915 | D8: 7063 | E8: 8288 | F8: 5969 | G8: 8962 | H8: 6894 | I8: 8953 | J8: 9510 | K8: 5125 | L8: 8662 | M8: 9429 | N8: =SUM(B8:M8) -> 90563
A9: Milk | B9: 7550 | C9: 8696 | D9: 6058 | E9: 7097 | F9: 8525 | G9: 6687 | H9: 9816 | I9: 9814 | J9: 5544 | K9: 5882 | L9: 8039 | M9: 5684 | N9: =SUM(B9:M9) -> 89392
A10: Milo | B10: 9215 | C10: 7174 | D10: 8891 | E10: 7670 | F10: 9451 | G10: 7288 | H10: 5357 | I10: 9858 | J10: 9792 | K10: 8711 | L10: 8980 | M10: 5778 | N10: =SUM(B10:M10) -> 98165
A12: Grand total | N12: =SUM(N3:N10) -> 731031

Sheet South Branch
A1: ABC Supermarket Sales for 2025
A2: Product | B2: January | C2: February | D2: March | E2: April | F2: May | G2: June | H2: July | I2: August | J2: September | K2: October | L2: November | M2: December | N2: Total
A3: Rice | B3: 9349 | C3: 6134 | D3: 8763 | E3: 8355 | F3: 6682 | G3: 9355 | H3: 9607 | I3: 7465 | J3: 7805 | K3: 8174 | L3: 9803 | M3: 7693 | N3: 99185
A4: Beans | B4: 8024 | C4: 6942 | D4: 6268 | E4: 5875 | F4: 5902 | G4: 7859 | H4: 9892 | I4: 8654 | J4: 8022 | K4: 8431 | L4: 8544 | M4: 9592 | N4: 94005
A5: Butter | B5: 5351 | C5: 7798 | D5: 5147 | E5: 9168 | F5: 6893 | G5: 9124 | H5: 5653 | I5: 8040 | J5: 9816 | K5: 9921 | L5: 9541 | M5: 9980 | N5: 96432
A6: Gum | B6: 6024 | C6: 9978 | D6: 5225 | E6: 7820 | F6: 7337 | G6: 9767 | H6: 5494 | I6: 6431 | J6: 8542 | K6: 7064 | L6: 8563 | M6: 7769 | N6: 90014
A7: Bread | B7: 6188 | C7: 8504 | D7: 7320 | E7: 8009 | F7: 8774 | G7: 8107 | H7: 7281 | I7: 7904 | J7: 7079 | K7: 8406 | L7: 9083 | M7: 8307 | N7: 94962
A8: Ice Cream | B8: 8297 | C8: 5959 | D8: 6308 | E8: 5875 | F8: 9144 | G8: 5655 | H8: 8162 | I8: 9960 | J8: 8253 | K8: 9664 | L8: 7860 | M8: 6828 | N8: 91965
A9: Milk | B9: 5852 | C9: 6560 | D9: 7852 | E9: 8791 | F9: 5966 | G9: 5490 | H9: 9316 | I9: 7915 | J9: 8651 | K9: 9142 | L9: 6272 | M9: 8702 | N9: 90509
A10: Milo | B10: 5043 | C10: 9350 | D10: 9991 | E10: 7267 | F10: 7359 | G10: 8726 | H10: 8214 | I10: 6927 | J10: 5444 | K10: 5376 | L10: 5428 | M10: 5112 | N10: 84237
A12: Grand total | N12: 741309

Sheet East Branch
A1: ABC Supermarket Sales for 2025
A2: Product | B2: January | C2: February | D2: March | E2: April | F2: May | G2: June | H2: July | I2: August | J2: September | K2: October | L2: November | M2: December | N2: Total
A3: Rice | B3: 7333 | C3: 7897 | D3: 6722 | E3: 6116 | F3: 6254 | G3: 5054 | H3: 6014 | I3: 5913 | J3: 5786 | K3: 6577 | L3: 7090 | M3: 7781 | N3: 78537
A4: Beans | B4: 8625 | C4: 6646 | D4: 8067 | E4: 5056 | F4: 9026 | G4: 9601 | H4: 8159 | I4: 8581 | J4: 7890 | K4: 7915 | L4: 7858 | M4: 6444 | N4: 93868
A5: Butter | B5: 8856 | C5: 7206 | D5: 6849 | E5: 9337 | F5: 5423 | G5: 5331 | H5: 8655 | I5: 5805 | J5: 5194 | K5: 7354 | L5: 5877 | M5: 9226 | N5: 85113
A6: Gum | B6: 8333 | C6: 6323 | D6: 6395 | E6: 8901 | F6: 5065 | G6: 9585 | H6: 7877 | I6: 8151 | J6: 8494 | K6: 9812 | L6: 9792 | M6: 8106 | N6: 96834
A7: Bread | B7: 8118 | C7: 8992 | D7: 9524 | E7: 5955 | F7: 8290 | G7: 7994 | H7: 8187 | I7: 9087 | J7: 5981 | K7: 7927 | L7: 9691 | M7: 5929 | N7: 95675
A8: Ice Cream | B8: 8741 | C8: 9540 | D8: 7839 | E8: 9116 | F8: 9002 | G8: 7555 | H8: 5123 | I8: 5982 | J8: 6471 | K8: 9520 | L8: 8766 | M8: 8754 | N8: 96409
A9: Milk | B9: 8318 | C9: 7702 | D9: 5015 | E9: 5547 | F9: 5005 | G9: 6678 | H9: 7164 | I9: 9094 | J9: 9761 | K9: 5662 | L9: 8537 | M9: 5967 | N9: 84450
A10: Milo | B10: 8834 | C10: 9901 | D10: 9629 | E10: 9345 | F10: 7597 | G10: 9989 | H10: 6555 | I10: 6413 | J10: 9131 | K10: 5250 | L10: 6039 | M10: 7728 | N10: 96411
A12: Grand total | N12: =SUM(N3:N10) -> 727297

Sheet West Branch
A1: ABC Supermarket Sales for 2025
A2: Product | B2: January | C2: February | D2: March | E2: April | F2: May | G2: June | H2: July | I2: August | J2: September | K2: October | L2: November | M2: December | N2: Total
A3: Rice | B3: =SUM(RANDBETWEEN(5000,10000)) -> 6277 | C3: =SUM(RANDBETWEEN(5000,10000)) -> 5088 | D3: =SUM(RANDBETWEEN(5000,10000)) -> 7613 | E3: =SUM(RANDBETWEEN(5000,10000)) -> 8130 | F3: =SUM(RANDBETWEEN(5000,10000)) -> 8353 | G3: =SUM(RANDBETWEEN(5000,10000)) -> 9292 | H3: =SUM(RANDBETWEEN(5000,10000)) -> 8321 | I3: =SUM(RANDBETWEEN(5000,10000)) -> 5193 | ... M3: =SUM(RANDBETWEEN(5000,10000)) -> 8316 | N3: =SUM(B3:M3) -> 90296
A4: Beans | B4: =SUM(RANDBETWEEN(5000,10000)) -> 5425 | C4: =SUM(RANDBETWEEN(5000,10000)) -> 6042 | D4: =SUM(RANDBETWEEN(5000,10000)) -> 9718 | E4: =SUM(RANDBETWEEN(5000,10000)) -> 9317 | F4: =SUM(RANDBETWEEN(5000,10000)) -> 5250 | G4: =SUM(RANDBETWEEN(5000,10000)) -> 5548 | H4: =SUM(RANDBETWEEN(5000,10000)) -> 7908 | I4: =SUM(RANDBETWEEN(5000,10000)) -> 9617 | ... M4: =SUM(RANDBETWEEN(5000,10000)) -> 7574 | N4: =SUM(B4:M4) -> 88010
A5: Butter | B5: =SUM(RANDBETWEEN(5000,10000)) -> 7558 | C5: =SUM(RANDBETWEEN(5000,10000)) -> 9528 | D5: =SUM(RANDBETWEEN(5000,10000)) -> 8550 | E5: =SUM(RANDBETWEEN(5000,10000)) -> 7262 | F5: =SUM(RANDBETWEEN(5000,10000)) -> 5604 | G5: =SUM(RANDBETWEEN(5000,10000)) -> 6205 | H5: =SUM(RANDBETWEEN(5000,10000)) -> 5225 | I5: =SUM(RANDBETWEEN(5000,10000)) -> 6668 | ... M5: =SUM(RANDBETWEEN(5000,10000)) -> 8076 | N5: =SUM(B5:M5) -> 85572
A6: Gum | B6: =SUM(RANDBETWEEN(5000,10000)) -> 6452 | C6: =SUM(RANDBETWEEN(5000,10000)) -> 6681 | D6: =SUM(RANDBETWEEN(5000,10000)) -> 9929 | E6: =SUM(RANDBETWEEN(5000,10000)) -> 5686 | F6: =SUM(RANDBETWEEN(5000,10000)) -> 6391 | G6: =SUM(RANDBETWEEN(5000,10000)) -> 5829 | H6: =SUM(RANDBETWEEN(5000,10000)) -> 8259 | I6: =SUM(RANDBETWEEN(5000,10000)) -> 8724 | ... M6: =SUM(RANDBETWEEN(5000,10000)) -> 8156 | N6: =SUM(B6:M6) -> 91861
A7: Bread | B7: =SUM(RANDBETWEEN(5000,10000)) -> 8641 | C7: =SUM(RANDBETWEEN(5000,10000)) -> 5214 | D7: =SUM(RANDBETWEEN(5000,10000)) -> 9677 | E7: =SUM(RANDBETWEEN(5000,10000)) -> 6470 | F7: =SUM(RANDBETWEEN(5000,10000)) -> 8775 | G7: =SUM(RANDBETWEEN(5000,10000)) -> 9429 | H7: =SUM(RANDBETWEEN(5000,10000)) -> 8986 | I7: =SUM(RANDBETWEEN(5000,10000)) -> 5230 | ... M7: =SUM(RANDBETWEEN(5000,10000)) -> 7747 | N7: =SUM(B7:M7) -> 95927
A8: Ice Cream | B8: =SUM(RANDBETWEEN(5000,10000)) -> 7564 | C8: =SUM(RANDBETWEEN(5000,10000)) -> 7119 | D8: =SUM(RANDBETWEEN(5000,10000)) -> 5946 | E8: =SUM(RANDBETWEEN(5000,10000)) -> 6653 | F8: =SUM(RANDBETWEEN(5000,10000)) -> 9734 | G8: =SUM(RANDBETWEEN(5000,10000)) -> 5720 | H8: =SUM(RANDBETWEEN(5000,10000)) -> 9516 | I8: =SUM(RANDBETWEEN(5000,10000)) -> 8140 | ... M8: =SUM(RANDBETWEEN(5000,10000)) -> 9679 | N8: =SUM(B8:M8) -> 95184
A9: Milk | B9: =SUM(RANDBETWEEN(5000,10000)) -> 6192 | C9: =SUM(RANDBETWEEN(5000,10000)) -> 6313 | D9: =SUM(RANDBETWEEN(5000,10000)) -> 7981 | E9: =SUM(RANDBETWEEN(5000,10000)) -> 5696 | F9: =SUM(RANDBETWEEN(5000,10000)) -> 8741 | G9: =SUM(RANDBETWEEN(5000,10000)) -> 5220 | H9: =SUM(RANDBETWEEN(5000,10000)) -> 8719 | I9: =SUM(RANDBETWEEN(5000,10000)) -> 5764 | ... M9: =SUM(RANDBETWEEN(5000,10000)) -> 8446 | N9: =SUM(B9:M9) -> 86519
A10: Milo | B10: =SUM(RANDBETWEEN(5000,10000)) -> 7268 | C10: =SUM(RANDBETWEEN(5000,10000)) -> 5676 | D10: =SUM(RANDBETWEEN(5000,10000)) -> 5398 | E10: =SUM(RANDBETWEEN(5000,10000)) -> 7635 | F10: =SUM(RANDBETWEEN(5000,10000)) -> 8810 | G10: =SUM(RANDBETWEEN(5000,10000)) -> 9906 | H10: =SUM(RANDBETWEEN(5000,10000)) -> 7759 | I10: =SUM(RANDBETWEEN(5000,10000)) -> 8497 | ... M10: =SUM(RANDBETWEEN(5000,10000)) -> 9297 | N10: =SUM(B10:M10) -> 92649
A12: Grand total | N12: =SUM(N3:N10) -> 726018
